[
  {
    "id": 1,
    "source": "IMPASTO PER PIZZA PAZZESCO! CON 50% BIGA FREDDA/PREFERMENTO",
    "url": "https://www.youtube.com/watch?v=cmaKBHBaWfw",
    "bigaHyd": 50,
    "yeastPct": 0.4,
    "flourTemp": 20,
    "waterTemp": 20,
    "useRT": true,
    "rtHours": 2.0,
    "rtTemp": 20,
    "restTemp": 4,
    "expectedHours": { "min": 20, "max": 22 },
    "notes": "Water temp 4°C in summer / RT in winter — using summer (worst case). Yeast 0.4% vs model's 1%."
  },
  {
    "id": 2,
    "source": "PIZZA NAPOLETANA CON BIGA - La Ricetta di Malati di Pizza",
    "url": "https://www.youtube.com/watch?v=ZVU9D4OkviM&t=465s",
    "bigaHyd": 50,
    "yeastPct": 1.0,
    "flourTemp": 20,
    "waterTemp": 4,
    "useRT": true,
    "rtHours": 0.33,
    "rtTemp": 20,
    "restTemp": 4,
    "expectedHours": { "min": 16, "max": 24 },
    "notes": "Kickstart is only 20 min (0.33h) — below UI slider minimum of 0.5h but valid for the model."
  },
  {
    "id": 3,
    "source": "Come fare la BIGA ANCHE A CASA - il tutorial definitivo e completo (60% biga)",
    "url": "https://www.youtube.com/watch?v=5SleVVMDWCQ",
    "bigaHyd": 60,
    "yeastPct": 1.0,
    "flourTemp": 20,
    "waterTemp": 20,
    "useRT": true,
    "rtHours": 1.0,
    "rtTemp": 20,
    "restTemp": 4,
    "expectedHours": { "min": 22, "max": 24 },
    "notes": "Water and kickstart at room temperature (20°C)."
  },
  {
    "id": 4,
    "source": "Come fare la BIGA ANCHE A CASA - il tutorial definitivo e completo (44% biga, 18°C)",
    "url": "Come fare la BIGA ANCHE A CASA - il tutorial definitivo e completo (44% biga, 18°C)",
    "bigaHyd": 44,
    "yeastPct": 1.0,
    "flourTemp": 20,
    "waterTemp": 20,
    "useRT": false,
    "rtHours": 0,
    "rtTemp": 20,
    "restTemp": 18,
    "expectedHours": { "min": 18, "max": 20 },
    "notes": "Room-temperature fermentation, no kickstart."
  },
  {
    "id": 5,
    "source": "BIGA - COME CREARLA E GESTIRLA - TUTTI I SEGRETI!",
    "url": "https://www.youtube.com/watch?v=6Se-gtyAdIY",
    "bigaHyd": 50,
    "yeastPct": 0.5,
    "flourTemp": 20,
    "waterTemp": 20,
    "useRT": true,
    "rtHours": 3.0,
    "rtTemp": 20,
    "restTemp": 4,
    "expectedHours": { "min": 20, "max": 24 },
    "notes": "Yeast 0.5% vs model's 1%. Long RT kickstart (3h) before cold rest."
  },
  {
    "id": 6,
    "source": "BIGA FREDDA: gestione del prefemento in frigo",
    "url": "https://www.youtube.com/watch?v=WansgZ5TxxI&t=342s",
    "bigaHyd": 60,
    "yeastPct": 1.0,
    "flourTemp": 20,
    "waterTemp": 20,
    "useRT": true,
    "rtHours": 0.5,
    "rtTemp": 23,
    "restTemp": 4,
    "expectedHours": { "min": 21, "max": 24 },
    "notes": "Kickstart at 23°C (slightly warm room)."
  },
  {
    "id": 7,
    "source": "Pizza napoletana con metodo biga 🍕",
    "url": "https://www.youtube.com/watch?v=yupuPNVwBuI&t=180s",
    "bigaHyd": 50,
    "yeastPct": 0.5,
    "flourTemp": 20,
    "waterTemp": 10,
    "useRT": false,
    "rtHours": 0,
    "rtTemp": 20,
    "restTemp": 18,
    "expectedHours": { "min": 16, "max": 18 },
    "notes": "Room-temperature fermentation with cold water (10°C). Yeast 0.5% vs model's 1%."
  },
  {
    "id": 8,
    "source": "PIZZA CONTEMPORANEA DI VINCENZO CAPUANO - 50% BIGA (video completo)",
    "url": "https://www.youtube.com/watch?v=GHm-x6Cy0VU",
    "bigaHyd": 50,
    "yeastPct": 0.75,
    "flourTemp": 20,
    "waterTemp": 4,
    "useRT": false,
    "rtHours": 0,
    "rtTemp": 20,
    "restTemp": 20,
    "expectedHours": { "min": 14, "max": 16 },
    "notes": "Warm rest (20°C) with cold water (4°C). Yeast 0.75% vs model's 1%."
  },
  {
    "id": 9,
    "source": "PIZZA IN TEGLIA 100% BIGA CON SBATTITORE! - ALTA IDRATAZIONE",
    "url": null,
    "bigaHyd": 50,
    "yeastPct": 1.0,
    "flourTemp": 20,
    "waterTemp": 10,
    "useRT": false,
    "rtHours": 0,
    "rtTemp": 20,
    "restTemp": 4,
    "expectedHours": { "min": 21, "max": 24 },
    "notes": "Cold rest with 10°C water."
  },
  {
    "id": 10,
    "source": "theromanobaker.com.au",
    "url": "https://www.theromanobaker.com.au/videos?wix-vod-video-id=afc7adb9fb40449a8bff4a7566042e53&wix-vod-comp-id=comp-lccouh5w",
    "bigaHyd": 45,
    "yeastPct": 1.0,
    "flourTemp": 20,
    "waterTemp": 4,
    "useRT": false,
    "rtHours": 0,
    "rtTemp": 20,
    "restTemp": 16,
    "expectedHours": { "min": 16, "max": 19 },
    "notes": "Cool (not cold) rest at 16°C with 4°C water."
  },
  {
    "id": 11,
    "source": "gumroad.com recipe",
    "url": "https://gumroad.com/d/7a109bc8b733ad4760ba0a2863a63cb8",
    "bigaHyd": 50,
    "yeastPct": 1.0,
    "flourTemp": 20,
    "waterTemp": 30,
    "useRT": false,
    "rtHours": 0,
    "rtTemp": 20,
    "restTemp": 4,
    "expectedHours": { "min": 20, "max": 24 },
    "notes": "Very warm water (30°C) — biga starts ~26°C and cools to 4°C fridge. Tests thermal model with large delta."
  },
  {
    "id": 12,
    "source": "TikTok @scuderi_alessandro",
    "url": "https://www.tiktok.com/@scuderi_alessandro/video/7515353335470296343",
    "bigaHyd": 60,
    "yeastPct": 1.0,
    "flourTemp": 20,
    "waterTemp": 20,
    "useRT": true,
    "rtHours": 0.5,
    "rtTemp": 20,
    "restTemp": 4,
    "expectedHours": { "min": 16, "max": 19 },
    "notes": "Short RT kickstart (30 min) at room temperature."
  },
  {
    "id": 13,
    "source": "Instagram Christian",
    "url": null,
    "bigaHyd": 60,
    "yeastPct": 1.0,
    "flourTemp": 20,
    "waterTemp": 8,
    "useRT": false,
    "rtHours": 0,
    "rtTemp": 20,
    "restTemp": 4,
    "expectedHours": { "min": 48, "max": 48 },
    "notes": "Very long cold rest (48h). Model likely predicts less — tests upper limits of cold fermentation."
  },
  {
    "id": 14,
    "source": "Recette de Pâte à Pizza Professionnelle, Napolitaine Contemporaine",
    "url": null,
    "bigaHyd": 60,
    "yeastPct": 0.4,
    "flourTemp": 20,
    "waterTemp": 20,
    "useRT": false,
    "rtHours": 0,
    "rtTemp": 20,
    "restTemp": 4,
    "expectedHours": { "min": 48, "max": 48 },
    "notes": "Very low yeast (0.4%) with cold rest. Model (1% yeast) will predict much shorter time — large known gap."
  }
]
